bottle_peewee.py
bottle_peewee-0.1.5.dist-info/DESCRIPTION.rst
bottle_peewee-0.1.5.dist-info/METADATA
bottle_peewee-0.1.5.dist-info/metadata.json
bottle_peewee-0.1.5.dist-info/RECORD
bottle_peewee-0.1.5.dist-info/top_level.txt
bottle_peewee-0.1.5.dist-info/WHEEL
